extasycoco/__init__.py
extasycoco/_version.py
extasycoco/coco.py
extasycoco/mapping.py
extasycoco/mc.py
extasycoco-0.4.1.data/scripts/pyCoCo
extasycoco-0.4.1.data/scripts/pyCoCoMC
extasycoco-0.4.1.dist-info/LICENSE.txt
extasycoco-0.4.1.dist-info/METADATA
extasycoco-0.4.1.dist-info/WHEEL
extasycoco-0.4.1.dist-info/top_level.txt
extasycoco-0.4.1.dist-info/RECORD
